[
  {
    "EmployeeID": 5,
    "Last_Name": "Binder",
    "First_Name": "Dan",
    "Ext": 4595,
    "Title": "Research Analyst",
    "Dept": "R & D",
    "EMailAddress": "DBinder@aqua-aerobic.com",
    "Manager": "NULL",
    "Photo": "NULL",
    "FloorMap": "NULL",
    "URL": "https://aquaaerobicsystem.github.io/aquadirectory/index.html?app=aquadirectory&width=715&height=21&floor=first",
    "Location": ""
  },
  {
    "EmployeeID": 10,
    "Last_Name": "Brown",
    "First_Name": "Gordy",
    "Ext": 4422,
    "Title": "Engineer",
    "Dept": "Engineering",
    "EMailAddress": "GBrown@aqua-aerobic.com",
    "Manager": "NULL",
    "Photo": "NULL",
    "FloorMap": "NULL",
    "URL": "https://aquaaerobicsystem.github.io/aquadirectory/index.html?app=aquadirectory&width=715&height=21&floor=first",
    "Location": ""
  },
  {
    "EmployeeID": 13,
    "Last_Name": "Cornford",
    "First_Name": "Dave",
    "Ext": 4439,
    "Title": "Project Manager",
    "Dept": "Engineering",
    "EMailAddress": "DCornford@aqua-aerobic.com",
    "Manager": "NULL",
    "Photo": "NULL",
    "FloorMap": "NULL",
    "URL": "https://aquaaerobicsystem.github.io/aquadirectory/index.html?app=aquadirectory&width=715&height=21&floor=first",
    "Location": ""
  },
  {
    "EmployeeID": 18,
    "Last_Name": "Heasley",
    "First_Name": "Deborah",
    "Ext": 4527,
    "Title": "International Business Specialist",
    "Dept": "Contract Administration",
    "EMailAddress": "DHeasley@aqua-aerobic.com",
    "Manager": "NULL",
    "Photo": "NULL",
    "FloorMap": "NULL",
    "URL": "https://aquaaerobicsystem.github.io/aquadirectory/index.html?app=aquadirectory&width=715&height=21&floor=first",
    "Location": ""
  },
  {
    "EmployeeID": 19,
    "Last_Name": "Herbig",
    "First_Name": "Mark",
    "Ext": 4549,
    "Title": "Supervisor, Contract Engineering",
    "Dept": "Engineering",
    "EMailAddress": "MHerbig@aqua-aerobic.com",
    "Manager": "NULL",
    "Photo": "NULL",
    "FloorMap": "NULL",
    "URL": "https://aquaaerobicsystem.github.io/aquadirectory/index.html?app=aquadirectory&width=715&height=21&floor=first",
    "Location": ""
  },
  {
    "EmployeeID": 20,
    "Last_Name": "Herron",
    "First_Name": "Donnelle",
    "Ext": 4559,
    "Title": "Contract Administrator",
    "Dept": "Contract Administration",
    "EMailAddress": "DHerron@aqua-aerobic.com",
    "Manager": "NULL",
    "Photo": "NULL",
    "FloorMap": "NULL",
    "URL": "https://aquaaerobicsystem.github.io/aquadirectory/index.html?app=aquadirectory&width=715&height=21&floor=first",
    "Location": ""
  },
  {
    "EmployeeID": 27,
    "Last_Name": "Lyman",
    "First_Name": "Staci",
    "Ext": 4586,
    "Title": "Contract Administrator",
    "Dept": "Contract Administration",
    "EMailAddress": "SLyman@aqua-aerobic.com",
    "Manager": "NULL",
    "Photo": "NULL",
    "FloorMap": "NULL",
    "URL": "https://aquaaerobicsystem.github.io/aquadirectory/index.html?app=aquadirectory&width=715&height=21&floor=first",
    "Location": ""
  },
  {
    "EmployeeID": 28,
    "Last_Name": "Klebs",
    "First_Name": "Paul",
    "Ext": 4466,
    "Title": "AfterMarket Sales Manager",
    "Dept": "AfterMarket Sales",
    "EMailAddress": "PKlebs@aqua-aerobic.com",
    "Manager": "NULL",
    "Photo": "NULL",
    "FloorMap": "NULL",
    "URL": "https://aquaaerobicsystem.github.io/aquadirectory/index.html?app=aquadirectory&width=715&height=21&floor=first",
    "Location": ""
  },
  {
    "EmployeeID": 29,
    "Last_Name": "Knight",
    "First_Name": "James A.",
    "Ext": 4538,
    "Title": "Rotating Products – Senior Engineer",
    "Dept": "Engineering",
    "EMailAddress": "JKnight@aqua-aerobic.com",
    "Manager": "NULL",
    "Photo": "NULL",
    "FloorMap": "NULL",
    "URL": "https://aquaaerobicsystem.github.io/aquadirectory/index.html?app=aquadirectory&width=715&height=21&floor=first",
    "Location": ""
  },
  {
    "EmployeeID": 35,
    "Last_Name": "Lenox",
    "First_Name": "Mark",
    "Ext": 4584,
    "Title": "Senior Mechanical Designer",
    "Dept": "Engineering",
    "EMailAddress": "MLenox@aqua-aerobic.com",
    "Manager": "NULL",
    "Photo": "NULL",
    "FloorMap": "NULL",
    "URL": "https://aquaaerobicsystem.github.io/aquadirectory/index.html?app=aquadirectory&width=715&height=21&floor=first",
    "Location": ""
  },
  {
    "EmployeeID": 39,
    "Last_Name": "Meyer",
    "First_Name": "Pat",
    "Ext": 4588,
    "Title": "Accounting Assistant",
    "Dept": "Accounting",
    "EMailAddress": "PMeyer@aqua-aerobic.com",
    "Manager": "NULL",
    "Photo": "NULL",
    "FloorMap": "NULL",
    "URL": "https://aquaaerobicsystem.github.io/aquadirectory/index.html?app=aquadirectory&width=715&height=21&floor=first",
    "Location": ""
  },
  {
    "EmployeeID": 44,
    "Last_Name": "Nelson",
    "First_Name": "Paul",
    "Ext": 4554,
    "Title": "Southeast Regional Manager",
    "Dept": "Domestic Sales",
    "EMailAddress": "PNelson@aqua-aerobic.com",
    "Manager": "NULL",
    "Photo": "NULL",
    "FloorMap": "NULL",
    "URL": "https://aquaaerobicsystem.github.io/aquadirectory/index.html?app=aquadirectory&width=715&height=21&floor=first",
    "Location": ""
  },
  {
    "EmployeeID": 45,
    "Last_Name": "Pippel",
    "First_Name": "Cindy",
    "Ext": 4477,
    "Title": "Supervisor, Contract Administration",
    "Dept": "Contract Administration",
    "EMailAddress": "CPippel@aqua-aerobic.com",
    "Manager": "NULL",
    "Photo": "NULL",
    "FloorMap": "NULL",
    "URL": "https://aquaaerobicsystem.github.io/aquadirectory/index.html?app=aquadirectory&width=715&height=21&floor=first",
    "Location": ""
  },
  {
    "EmployeeID": 48,
    "Last_Name": "Reid, P.E.",
    "First_Name": "Terry",
    "Ext": 4509,
    "Title": "Product Manager, Biological Processes & Membranes",
    "Dept": "Applications Engineering",
    "EMailAddress": "TReid@aqua-aerobic.com",
    "Manager": "NULL",
    "Photo": "NULL",
    "FloorMap": "NULL",
    "URL": "https://aquaaerobicsystem.github.io/aquadirectory/index.html?app=aquadirectory&width=715&height=21&floor=first",
    "Location": ""
  },
  {
    "EmployeeID": 78,
    "Last_Name": "Kunz",
    "First_Name": "Cheryl",
    "Ext": 4582,
    "Title": "Advertising And Public Relations Manager",
    "Dept": "Marketing",
    "EMailAddress": "CKunz@aqua-aerobic.com",
    "Manager": "NULL",
    "Photo": "NULL",
    "FloorMap": "NULL",
    "URL": "https://aquaaerobicsystem.github.io/aquadirectory/index.html?app=aquadirectory&width=715&height=21&floor=first",
    "Location": ""
  },
  {
    "EmployeeID": 84,
    "Last_Name": "Sudds",
    "First_Name": "Sara",
    "Ext": 4541,
    "Title": "Accounting Assistant",
    "Dept": "Accounting",
    "EMailAddress": "SSudds@aqua-aerobic.com",
    "Manager": "NULL",
    "Photo": "NULL",
    "FloorMap": "NULL",
    "URL": "https://aquaaerobicsystem.github.io/aquadirectory/index.html?app=aquadirectory&width=715&height=21&floor=first",
    "Location": ""
  },
  {
    "EmployeeID": 85,
    "Last_Name": "Willis",
    "First_Name": "Scott",
    "Ext": 4526,
    "Title": "Vice President and Chief Financial Officer",
    "Dept": "Accounting",
    "EMailAddress": "SWillis@aqua-aerobic.com",
    "Manager": "NULL",
    "Photo": "NULL",
    "FloorMap": "NULL",
    "URL": "https://aquaaerobicsystem.github.io/aquadirectory/index.html?app=aquadirectory&width=715&height=21&floor=first",
    "Location": ""
  },
  {
    "EmployeeID": 129,
    "Last_Name": "Baumann, P.E.",
    "First_Name": "Peter G.",
    "Ext": 4561,
    "Title": "Chief Operating Officer",
    "Dept": "Process Group",
    "EMailAddress": "PBaumann@aqua-aerobic.com",
    "Manager": "NULL",
    "Photo": "NULL",
    "FloorMap": "NULL",
    "URL": "https://aquaaerobicsystem.github.io/aquadirectory/index.html?app=aquadirectory&width=715&height=21&floor=first",
    "Location": ""
  },
  {
    "EmployeeID": 145,
    "Last_Name": "Wiegand",
    "First_Name": "Robert",
    "Ext": 4476,
    "Title": "Electrical Engineer Manager",
    "Dept": "Engineering",
    "EMailAddress": "RWiegand@aqua-aerobic.com",
    "Manager": "NULL",
    "Photo": "NULL",
    "FloorMap": "NULL",
    "URL": "https://aquaaerobicsystem.github.io/aquadirectory/index.html?app=aquadirectory&width=715&height=21&floor=first",
    "Location": ""
  },
  {
    "EmployeeID": 150,
    "Last_Name": "Kellogg",
    "First_Name": "Jim",
    "Ext": 1302,
    "Title": "Field Service Representative",
    "Dept": "Field Service",
    "EMailAddress": "JKellogg@aqua-aerobic.com",
    "Manager": "NULL",
    "Photo": "NULL",
    "FloorMap": "NULL",
    "URL": "https://aquaaerobicsystem.github.io/aquadirectory/index.html?app=aquadirectory&width=715&height=21&floor=first",
    "Location": ""
  },
  {
    "EmployeeID": 151,
    "Last_Name": "See",
    "First_Name": "Douglas",
    "Ext": 1308,
    "Title": "Field Service Representative",
    "Dept": "Field Service",
    "EMailAddress": "DSee@aqua-aerobic.com",
    "Manager": "NULL",
    "Photo": "NULL",
    "FloorMap": "NULL",
    "URL": "https://aquaaerobicsystem.github.io/aquadirectory/index.html?app=aquadirectory&width=715&height=21&floor=first",
    "Location": ""
  },
  {
    "EmployeeID": 173,
    "Last_Name": "Lamont",
    "First_Name": "Tim",
    "Ext": 4515,
    "Title": "Senior Customer Service Representative",
    "Dept": "Parts Sales",
    "EMailAddress": "TLamont@aqua-aerobic.com",
    "Manager": "NULL",
    "Photo": "NULL",
    "FloorMap": "NULL",
    "URL": "https://aquaaerobicsystem.github.io/aquadirectory/index.html?app=aquadirectory&width=715&height=21&floor=first",
    "Location": ""
  },
  {
    "EmployeeID": 176,
    "Last_Name": "Pass",
    "First_Name": "Brian",
    "Ext": 4478,
    "Title": "Senior Electrical Designer",
    "Dept": "Engineering",
    "EMailAddress": "BPass@aqua-aerobic.com",
    "Manager": "NULL",
    "Photo": "NULL",
    "FloorMap": "NULL",
    "URL": "https://aquaaerobicsystem.github.io/aquadirectory/index.html?app=aquadirectory&width=715&height=21&floor=first",
    "Location": ""
  },
  {
    "EmployeeID": 177,
    "Last_Name": "Johnson",
    "First_Name": "David",
    "Ext": 4479,
    "Title": "Electrical Engineer",
    "Dept": "Engineering",
    "EMailAddress": "Dave.Johnson@aqua-aerobic.com",
    "Manager": "NULL",
    "Photo": "NULL",
    "FloorMap": "NULL",
    "URL": "https://aquaaerobicsystem.github.io/aquadirectory/index.html?app=aquadirectory&width=715&height=21&floor=first",
    "Location": ""
  },
  {
    "EmployeeID": 180,
    "Last_Name": "Smith",
    "First_Name": "David",
    "Ext": 4421,
    "Title": "Manager, Mechanical Engineering",
    "Dept": "Engineering",
    "EMailAddress": "DSmith@aqua-aerobic.com",
    "Manager": "NULL",
    "Photo": "NULL",
    "FloorMap": "NULL",
    "URL": "https://aquaaerobicsystem.github.io/aquadirectory/index.html?app=aquadirectory&width=715&height=21&floor=first",
    "Location": ""
  },
  {
    "EmployeeID": 183,
    "Last_Name": "Heasley",
    "First_Name": "Kevin L.",
    "Ext": 4579,
    "Title": "Vice President",
    "Dept": "Operations",
    "EMailAddress": "KHeasley@aqua-aerobic.com",
    "Manager": "NULL",
    "Photo": "NULL",
    "FloorMap": "NULL",
    "URL": "https://aquaaerobicsystem.github.io/aquadirectory/index.html?app=aquadirectory&width=715&height=21&floor=first",
    "Location": ""
  },
  {
    "EmployeeID": 184,
    "Last_Name": "Horton",
    "First_Name": "James",
    "Ext": 4524,
    "Title": "Vice President - Process Group",
    "Dept": "Process Group",
    "EMailAddress": "JHorton@aqua-aerobic.com",
    "Manager": "NULL",
    "Photo": "NULL",
    "FloorMap": "NULL",
    "URL": "https://aquaaerobicsystem.github.io/aquadirectory/index.html?app=aquadirectory&width=715&height=21&floor=first",
    "Location": ""
  },
  {
    "EmployeeID": 194,
    "Last_Name": "Pike",
    "First_Name": "Sherry",
    "Ext": 4589,
    "Title": "Customer Service Representative",
    "Dept": "Parts Sales",
    "EMailAddress": "spike@aqua-aerobic.com",
    "Manager": "NULL",
    "Photo": "NULL",
    "FloorMap": "NULL",
    "URL": "https://aquaaerobicsystem.github.io/aquadirectory/index.html?app=aquadirectory&width=715&height=21&floor=first",
    "Location": ""
  },
  {
    "EmployeeID": 195,
    "Last_Name": "Brundige",
    "First_Name": "Bill",
    "Ext": 4475,
    "Title": "Senior Electrical Designer",
    "Dept": "Electrical",
    "EMailAddress": "bbrundige@aqua-aerobic.com",
    "Manager": "NULL",
    "Photo": "NULL",
    "FloorMap": "NULL",
    "URL": "https://aquaaerobicsystem.github.io/aquadirectory/index.html?app=aquadirectory&width=715&height=21&floor=first",
    "Location": ""
  },
  {
    "EmployeeID": 196,
    "Last_Name": "Bahr",
    "First_Name": "Beth",
    "Ext": 4546,
    "Title": "Mechanical Designer",
    "Dept": "Engineering",
    "EMailAddress": "Bbahr@aqua-aerobic.com",
    "Manager": "NULL",
    "Photo": "NULL",
    "FloorMap": "NULL",
    "URL": "https://aquaaerobicsystem.github.io/aquadirectory/index.html?app=aquadirectory&width=715&height=21&floor=first",
    "Location": ""
  },
  {
    "EmployeeID": 197,
    "Last_Name": "Hood",
    "First_Name": "Lynn",
    "Ext": 4581,
    "Title": "Field Service Coordinator",
    "Dept": "Field Service",
    "EMailAddress": "Lhood@aqua-aerobic.com",
    "Manager": "NULL",
    "Photo": "NULL",
    "FloorMap": "NULL",
    "URL": "https://aquaaerobicsystem.github.io/aquadirectory/index.html?app=aquadirectory&width=715&height=21&floor=first",
    "Location": ""
  },
  {
    "EmployeeID": 218,
    "Last_Name": "Massari",
    "First_Name": "Joe",
    "Ext": 4556,
    "Title": "-Enter Employee Title",
    "Dept": "-Enter Employee Department",
    "EMailAddress": "FirstInititalAndLastName@aqua-aerobic.com",
    "Manager": "NULL",
    "Photo": "NULL",
    "FloorMap": "NULL",
    "URL": "https://aquaaerobicsystem.github.io/aquadirectory/index.html?app=aquadirectory&width=715&height=21&floor=first",
    "Location": ""
  },
  {
    "EmployeeID": 220,
    "Last_Name": "Welsh",
    "First_Name": "Todd",
    "Ext": 4542,
    "Title": "Cost/Staff Accountant",
    "Dept": "Accounting",
    "EMailAddress": "TWelsh@aqua-aerobic.com",
    "Manager": "NULL",
    "Photo": "NULL",
    "FloorMap": "NULL",
    "URL": "https://aquaaerobicsystem.github.io/aquadirectory/index.html?app=aquadirectory&width=715&height=21&floor=first",
    "Location": ""
  },
  {
    "EmployeeID": 223,
    "Last_Name": "Johnson",
    "First_Name": "Brady",
    "Ext": 1314,
    "Title": "Field Service Representative",
    "Dept": "Field Service",
    "EMailAddress": "FirstInititalAndLastName@aqua-aerobic.com",
    "Manager": "NULL",
    "Photo": "NULL",
    "FloorMap": "NULL",
    "URL": "https://aquaaerobicsystem.github.io/aquadirectory/index.html?app=aquadirectory&width=715&height=21&floor=first",
    "Location": ""
  },
  {
    "EmployeeID": 225,
    "Last_Name": "Fenton",
    "First_Name": "Tom",
    "Ext": 4590,
    "Title": "Senior Project Manager",
    "Dept": "Project Management",
    "EMailAddress": "TFenton@aqua-aerobic.com",
    "Manager": "NULL",
    "Photo": "NULL",
    "FloorMap": "NULL",
    "URL": "https://aquaaerobicsystem.github.io/aquadirectory/index.html?app=aquadirectory&width=715&height=21&floor=first",
    "Location": ""
  },
  {
    "EmployeeID": 229,
    "Last_Name": "Machula",
    "First_Name": "Jerry",
    "Ext": 4536,
    "Title": "-Enter Employee Title",
    "Dept": "-Enter Employee Department",
    "EMailAddress": "gmachula@aqua-aerobic.com",
    "Manager": "NULL",
    "Photo": "NULL",
    "FloorMap": "NULL",
    "URL": "https://aquaaerobicsystem.github.io/aquadirectory/index.html?app=aquadirectory&width=715&height=21&floor=first",
    "Location": ""
  },
  {
    "EmployeeID": 234,
    "Last_Name": "Lin, P.E.",
    "First_Name": "Hui",
    "Ext": 4427,
    "Title": "Director of International Business",
    "Dept": "Applications Engineering",
    "EMailAddress": "HLin@aqua-aerobic.com",
    "Manager": "NULL",
    "Photo": "NULL",
    "FloorMap": "NULL",
    "URL": "https://aquaaerobicsystem.github.io/aquadirectory/index.html?app=aquadirectory&width=715&height=21&floor=first",
    "Location": ""
  },
  {
    "EmployeeID": 238,
    "Last_Name": "De Los Santos",
    "First_Name": "Manuel",
    "Ext": 4459,
    "Title": "International Business Manager – Latin America",
    "Dept": "Applications Engineering",
    "EMailAddress": "mdelossantos@aqua-aerobic.com",
    "Manager": "NULL",
    "Photo": "NULL",
    "FloorMap": "NULL",
    "URL": "https://aquaaerobicsystem.github.io/aquadirectory/index.html?app=aquadirectory&width=715&height=21&floor=first",
    "Location": ""
  },
  {
    "EmployeeID": 249,
    "Last_Name": "Van Laeke",
    "First_Name": "Georgia",
    "Ext": 4445,
    "Title": "Operations Assistant",
    "Dept": "Production Control",
    "EMailAddress": "GVanlaeke@aqua-aerobic.com",
    "Manager": "NULL",
    "Photo": "NULL",
    "FloorMap": "NULL",
    "URL": "https://aquaaerobicsystem.github.io/aquadirectory/index.html?app=aquadirectory&width=715&height=21&floor=first",
    "Location": ""
  },
  {
    "EmployeeID": 251,
    "Last_Name": "Hevey",
    "First_Name": "Michael",
    "Ext": 4468,
    "Title": "Electrical Engineer",
    "Dept": "Electrical",
    "EMailAddress": "Mhevey@aqua-aerobic.com",
    "Manager": "NULL",
    "Photo": "NULL",
    "FloorMap": "NULL",
    "URL": "https://aquaaerobicsystem.github.io/aquadirectory/index.html?app=aquadirectory&width=715&height=21&floor=first",
    "Location": ""
  },
  {
    "EmployeeID": 266,
    "Last_Name": "Carlson",
    "First_Name": "Jeff",
    "Ext": 4448,
    "Title": "Assistant Buyer",
    "Dept": "Production Control",
    "EMailAddress": "JCarlson@aqua-aerobic.com",
    "Manager": "NULL",
    "Photo": "NULL",
    "FloorMap": "NULL",
    "URL": "https://aquaaerobicsystem.github.io/aquadirectory/index.html?app=aquadirectory&width=715&height=21&floor=first",
    "Location": ""
  },
  {
    "EmployeeID": 278,
    "Last_Name": "Schneider, P.E.",
    "First_Name": "Gerald",
    "Ext": 4492,
    "Title": "Electrical Engineer",
    "Dept": "Electrical",
    "EMailAddress": "GSchneider@aqua-aerobic.com",
    "Manager": "NULL",
    "Photo": "NULL",
    "FloorMap": "NULL",
    "URL": "https://aquaaerobicsystem.github.io/aquadirectory/index.html?app=aquadirectory&width=715&height=21&floor=first",
    "Location": ""
  },
  {
    "EmployeeID": 281,
    "Last_Name": "Knapp",
    "First_Name": "Tamera",
    "Ext": 4493,
    "Title": "Applications Engineering Manager",
    "Dept": "Applications Engineering",
    "EMailAddress": "TKnapp@aqua-aerobic.com",
    "Manager": "NULL",
    "Photo": "NULL",
    "FloorMap": "NULL",
    "URL": "https://aquaaerobicsystem.github.io/aquadirectory/index.html?app=aquadirectory&width=715&height=21&floor=first",
    "Location": ""
  },
  {
    "EmployeeID": 282,
    "Last_Name": "Lightfoot",
    "First_Name": "Gary",
    "Ext": 4495,
    "Title": "Electrical Engineer",
    "Dept": "Engineering",
    "EMailAddress": "GLightfoot@aqua-aerobic.com",
    "Manager": "NULL",
    "Photo": "NULL",
    "FloorMap": "NULL",
    "URL": "https://aquaaerobicsystem.github.io/aquadirectory/index.html?app=aquadirectory&width=715&height=21&floor=first",
    "Location": ""
  },
  {
    "EmployeeID": 287,
    "Last_Name": "Jittawattanarat, Ph.D.",
    "First_Name": "Rungrod",
    "Ext": 4533,
    "Title": "Project Applications Engineer",
    "Dept": "Applications Engineering",
    "EMailAddress": "RJittawa@aqua-aerobic.com",
    "Manager": "NULL",
    "Photo": "NULL",
    "FloorMap": "NULL",
    "URL": "https://aquaaerobicsystem.github.io/aquadirectory/index.html?app=aquadirectory&width=715&height=21&floor=first",
    "Location": ""
  },
  {
    "EmployeeID": 289,
    "Last_Name": "Durdan",
    "First_Name": "Dan",
    "Ext": 4425,
    "Title": "Contract Engineering Supervisor",
    "Dept": "Engineering",
    "EMailAddress": "DDurdan@aqua-aerobic.com",
    "Manager": "NULL",
    "Photo": "NULL",
    "FloorMap": "NULL",
    "URL": "https://aquaaerobicsystem.github.io/aquadirectory/index.html?app=aquadirectory&width=715&height=21&floor=first",
    "Location": ""
  },
  {
    "EmployeeID": 295,
    "Last_Name": "Burns",
    "First_Name": "Dan",
    "Ext": 4592,
    "Title": "IT Infrastructure Architect",
    "Dept": "MIS",
    "EMailAddress": "DBurns@aqua-aerobic.com",
    "Manager": "NULL",
    "Photo": "NULL",
    "FloorMap": "NULL",
    "URL": "https://aquaaerobicsystem.github.io/aquadirectory/index.html?app=aquadirectory&width=715&height=21&floor=first",
    "Location": ""
  },
  {
    "EmployeeID": 297,
    "Last_Name": "Kinroth",
    "First_Name": "Barb",
    "Ext": 4567,
    "Title": "Contract Administrator",
    "Dept": "Contract Administration",
    "EMailAddress": "BKinroth@aqua-aerobic.com",
    "Manager": "NULL",
    "Photo": "NULL",
    "FloorMap": "NULL",
    "URL": "https://aquaaerobicsystem.github.io/aquadirectory/index.html?app=aquadirectory&width=715&height=21&floor=first",
    "Location": ""
  },
  {
    "EmployeeID": 300,
    "Last_Name": "Crews",
    "First_Name": "Dan",
    "Ext": 4471,
    "Title": "Electrical Engineer",
    "Dept": "Electrical",
    "EMailAddress": "DCrews@aqua-aerobic.com",
    "Manager": "NULL",
    "Photo": "NULL",
    "FloorMap": "NULL",
    "URL": "https://aquaaerobicsystem.github.io/aquadirectory/index.html?app=aquadirectory&width=715&height=21&floor=first",
    "Location": ""
  },
  {
    "EmployeeID": 307,
    "Last_Name": "Larson",
    "First_Name": "Curt",
    "Ext": 1304,
    "Title": "Field Service Representative",
    "Dept": "Customer Service",
    "EMailAddress": "Clarson@aqua-aerobic.com",
    "Manager": "NULL",
    "Photo": "NULL",
    "FloorMap": "NULL",
    "URL": "https://aquaaerobicsystem.github.io/aquadirectory/index.html?app=aquadirectory&width=715&height=21&floor=first",
    "Location": ""
  },
  {
    "EmployeeID": 311,
    "Last_Name": "Austin",
    "First_Name": "Tim",
    "Ext": 4452,
    "Title": "Mechanical Designer",
    "Dept": "Engineering",
    "EMailAddress": "TAustin@aqua-aerobic.com",
    "Manager": "NULL",
    "Photo": "NULL",
    "FloorMap": "NULL",
    "URL": "https://aquaaerobicsystem.github.io/aquadirectory/index.html?app=aquadirectory&width=715&height=21&floor=first",
    "Location": ""
  },
  {
    "EmployeeID": 312,
    "Last_Name": "Howarth",
    "First_Name": "Scott",
    "Ext": 4543,
    "Title": "Mechanical Designer",
    "Dept": "Engineering",
    "EMailAddress": "SHowarth@aqua-aerobic.com",
    "Manager": "NULL",
    "Photo": "NULL",
    "FloorMap": "NULL",
    "URL": "https://aquaaerobicsystem.github.io/aquadirectory/index.html?app=aquadirectory&width=715&height=21&floor=first",
    "Location": ""
  },
  {
    "EmployeeID": 314,
    "Last_Name": "Teeters",
    "First_Name": "Dennis",
    "Ext": 4504,
    "Title": "Electrical Engineer",
    "Dept": "Electrical",
    "EMailAddress": "DTeeters@aqua-aerobic.com",
    "Manager": "NULL",
    "Photo": "NULL",
    "FloorMap": "NULL",
    "URL": "https://aquaaerobicsystem.github.io/aquadirectory/index.html?app=aquadirectory&width=715&height=21&floor=first",
    "Location": ""
  },
  {
    "EmployeeID": 317,
    "Last_Name": "Holland",
    "First_Name": "David",
    "Ext": 4470,
    "Title": "Senior Applications Engineer",
    "Dept": "Applications Engineering",
    "EMailAddress": "DHolland@aqua-aerobic.com",
    "Manager": "NULL",
    "Photo": "NULL",
    "FloorMap": "NULL",
    "URL": "https://aquaaerobicsystem.github.io/aquadirectory/index.html?app=aquadirectory&width=715&height=21&floor=first",
    "Location": ""
  },
  {
    "EmployeeID": 320,
    "Last_Name": "Tripp",
    "First_Name": "Scott",
    "Ext": 4469,
    "Title": "Engineer",
    "Dept": "Engineering",
    "EMailAddress": "STripp@aqua-aerobic.com",
    "Manager": "NULL",
    "Photo": "NULL",
    "FloorMap": "NULL",
    "URL": "https://aquaaerobicsystem.github.io/aquadirectory/index.html?app=aquadirectory&width=715&height=21&floor=first",
    "Location": ""
  },
  {
    "EmployeeID": 323,
    "Last_Name": "Mowery",
    "First_Name": "Tom",
    "Ext": 1307,
    "Title": "Field Service Representative",
    "Dept": "Field Service",
    "EMailAddress": "TMowery@aqua-aerobic.com",
    "Manager": "NULL",
    "Photo": "NULL",
    "FloorMap": "NULL",
    "URL": "https://aquaaerobicsystem.github.io/aquadirectory/index.html?app=aquadirectory&width=715&height=21&floor=first",
    "Location": ""
  },
  {
    "EmployeeID": 325,
    "Last_Name": "Carlson",
    "First_Name": "Chris",
    "Ext": 4499,
    "Title": "Design Engineer",
    "Dept": "Engineering",
    "EMailAddress": "CCarlson@aqua-aerobic.com",
    "Manager": "NULL",
    "Photo": "NULL",
    "FloorMap": "NULL",
    "URL": "https://aquaaerobicsystem.github.io/aquadirectory/index.html?app=aquadirectory&width=715&height=21&floor=first",
    "Location": ""
  },
  {
    "EmployeeID": 328,
    "Last_Name": "Zaphel",
    "First_Name": "Mike",
    "Ext": 4576,
    "Title": "Production Control Planner",
    "Dept": "Production Control",
    "EMailAddress": "MZaphel@aqua-aerobic.com",
    "Manager": "NULL",
    "Photo": "NULL",
    "FloorMap": "NULL",
    "URL": "https://aquaaerobicsystem.github.io/aquadirectory/index.html?app=aquadirectory&width=715&height=21&floor=first",
    "Location": ""
  },
  {
    "EmployeeID": 330,
    "Last_Name": "Huber",
    "First_Name": "Ruth",
    "Ext": 4535,
    "Title": "Project Management Assistant",
    "Dept": "Project Management",
    "EMailAddress": "RHuber@aqua-aerobic.com",
    "Manager": "NULL",
    "Photo": "NULL",
    "FloorMap": "NULL",
    "URL": "https://aquaaerobicsystem.github.io/aquadirectory/index.html?app=aquadirectory&width=715&height=21&floor=first",
    "Location": ""
  },
  {
    "EmployeeID": 333,
    "Last_Name": "Receiving",
    "First_Name": "Phone",
    "Ext": 4565,
    "Title": "-Enter Employee Title",
    "Dept": "-Enter Employee Department",
    "EMailAddress": "FirstInititalAndLastName@aqua-aerobic.com",
    "Manager": "NULL",
    "Photo": "NULL",
    "FloorMap": "NULL",
    "URL": "https://aquaaerobicsystem.github.io/aquadirectory/index.html?app=aquadirectory&width=715&height=21&floor=first",
    "Location": ""
  },
  {
    "EmployeeID": 338,
    "Last_Name": "Groen",
    "First_Name": "Alicia",
    "Ext": 4501,
    "Title": "-Enter Employee Title",
    "Dept": "-Enter Employee Department",
    "EMailAddress": "FirstInititalAndLastName@aqua-aerobic.com",
    "Manager": "NULL",
    "Photo": "NULL",
    "FloorMap": "NULL",
    "URL": "https://aquaaerobicsystem.github.io/aquadirectory/index.html?app=aquadirectory&width=715&height=21&floor=first",
    "Location": ""
  },
  {
    "EmployeeID": 340,
    "Last_Name": "Schmitz",
    "First_Name": "Mike",
    "Ext": 4573,
    "Title": "Mechanical Designer",
    "Dept": "Engineering",
    "EMailAddress": "MSchmitz@aqua-aerobic.com",
    "Manager": "NULL",
    "Photo": "NULL",
    "FloorMap": "NULL",
    "URL": "https://aquaaerobicsystem.github.io/aquadirectory/index.html?app=aquadirectory&width=715&height=21&floor=first",
    "Location": ""
  },
  {
    "EmployeeID": 341,
    "Last_Name": "Try",
    "First_Name": "Jeremy",
    "Ext": 4440,
    "Title": "Electrical Engineer",
    "Dept": "Electrical",
    "EMailAddress": "JTry@aqua-aerobic.com",
    "Manager": "NULL",
    "Photo": "NULL",
    "FloorMap": "NULL",
    "URL": "https://aquaaerobicsystem.github.io/aquadirectory/index.html?app=aquadirectory&width=715&height=21&floor=first",
    "Location": ""
  },
  {
    "EmployeeID": 348,
    "Last_Name": "Armstrong",
    "First_Name": "Dick",
    "Ext": 1311,
    "Title": "Field Service Representative",
    "Dept": "Customer Service",
    "EMailAddress": "DArmstro@aqua-aerobic.com",
    "Manager": "NULL",
    "Photo": "NULL",
    "FloorMap": "NULL",
    "URL": "https://aquaaerobicsystem.github.io/aquadirectory/index.html?app=aquadirectory&width=715&height=21&floor=first",
    "Location": ""
  },
  {
    "EmployeeID": 355,
    "Last_Name": "Konkol",
    "First_Name": "Chuck",
    "Ext": 4574,
    "Title": "Programmer/Analyst",
    "Dept": "MIS",
    "EMailAddress": "ckonkol@aqua-aerobic.com",
    "Manager": "NULL",
    "Photo": "NULL",
    "FloorMap": "NULL",
    "URL": "https://aquaaerobicsystem.github.io/aquadirectory/index.html?app=aquadirectory&width=715&height=21&floor=first",
    "Location": ""
  },
  {
    "EmployeeID": 356,
    "Last_Name": "Naruz",
    "First_Name": "Randy",
    "Ext": 4410,
    "Title": "PC Technician",
    "Dept": "MIS",
    "EMailAddress": "RNaruz@aqua-aerobic.com",
    "Manager": "NULL",
    "Photo": "NULL",
    "FloorMap": "NULL",
    "URL": "https://aquaaerobicsystem.github.io/aquadirectory/index.html?app=aquadirectory&width=715&height=21&floor=first",
    "Location": ""
  },
  {
    "EmployeeID": 361,
    "Last_Name": "Parsons",
    "First_Name": "Kevin",
    "Ext": 1316,
    "Title": "Field Service Representative",
    "Dept": "Customer Service",
    "EMailAddress": "KParsons@aqua-aerobic.com",
    "Manager": "NULL",
    "Photo": "NULL",
    "FloorMap": "NULL",
    "URL": "https://aquaaerobicsystem.github.io/aquadirectory/index.html?app=aquadirectory&width=715&height=21&floor=first",
    "Location": ""
  },
  {
    "EmployeeID": 362,
    "Last_Name": "Lange",
    "First_Name": "Velvet",
    "Ext": 4569,
    "Title": "Production Control Warranty Administrator",
    "Dept": "Production Control",
    "EMailAddress": "VLange@aqua-aerobic.com",
    "Manager": "NULL",
    "Photo": "NULL",
    "FloorMap": "NULL",
    "URL": "https://aquaaerobicsystem.github.io/aquadirectory/index.html?app=aquadirectory&width=715&height=21&floor=first",
    "Location": ""
  },
  {
    "EmployeeID": 368,
    "Last_Name": "Melody",
    "First_Name": "Rose",
    "Ext": 4428,
    "Title": "Sales Executive Assistant",
    "Dept": "Marketing",
    "EMailAddress": "RMelody@aqua-aerobic.com",
    "Manager": "NULL",
    "Photo": "NULL",
    "FloorMap": "NULL",
    "URL": "https://aquaaerobicsystem.github.io/aquadirectory/index.html?app=aquadirectory&width=715&height=21&floor=first",
    "Location": ""
  },
  {
    "EmployeeID": 371,
    "Last_Name": "Zajac",
    "First_Name": "Becky",
    "Ext": 4446,
    "Title": "Contract Administrator",
    "Dept": "Contract Administration",
    "EMailAddress": "BZajac@aqua-aerobic.com",
    "Manager": "NULL",
    "Photo": "NULL",
    "FloorMap": "NULL",
    "URL": "https://aquaaerobicsystem.github.io/aquadirectory/index.html?app=aquadirectory&width=715&height=21&floor=first",
    "Location": ""
  },
  {
    "EmployeeID": 374,
    "Last_Name": "Decker",
    "First_Name": "Bill",
    "Ext": 4423,
    "Title": "Vice President & General Manager",
    "Dept": "Equipment & Services Group",
    "EMailAddress": "BDecker@aqua-aerobic.com",
    "Manager": "NULL",
    "Photo": "NULL",
    "FloorMap": "NULL",
    "URL": "https://aquaaerobicsystem.github.io/aquadirectory/index.html?app=aquadirectory&width=715&height=21&floor=first",
    "Location": ""
  },
  {
    "EmployeeID": 376,
    "Last_Name": "McCormick",
    "First_Name": "Mike",
    "Ext": 4510,
    "Title": "-Enter Employee Title",
    "Dept": "-Enter Employee Department",
    "EMailAddress": "MMcCormick@aqua-aerobic.com",
    "Manager": "NULL",
    "Photo": "NULL",
    "FloorMap": "NULL",
    "URL": "https://aquaaerobicsystem.github.io/aquadirectory/index.html?app=aquadirectory&width=715&height=21&floor=first",
    "Location": ""
  },
  {
    "EmployeeID": 377,
    "Last_Name": "Hughes",
    "First_Name": "Mark",
    "Ext": 4555,
    "Title": "Process Engineer",
    "Dept": "Biological Processes",
    "EMailAddress": "mhughes@aqua-aerobic.com",
    "Manager": "NULL",
    "Photo": "NULL",
    "FloorMap": "NULL",
    "URL": "https://aquaaerobicsystem.github.io/aquadirectory/index.html?app=aquadirectory&width=715&height=21&floor=first",
    "Location": ""
  },
  {
    "EmployeeID": 378,
    "Last_Name": "Pratt",
    "First_Name": "Tyrone",
    "Ext": 4447,
    "Title": "Customer Service Manager",
    "Dept": "Customer Service",
    "EMailAddress": "tpratt@aqua-aerobic.com",
    "Manager": "NULL",
    "Photo": "NULL",
    "FloorMap": "NULL",
    "URL": "https://aquaaerobicsystem.github.io/aquadirectory/index.html?app=aquadirectory&width=715&height=21&floor=first",
    "Location": ""
  },
  {
    "EmployeeID": 380,
    "Last_Name": "Anderson",
    "First_Name": "Ranee",
    "Ext": 4534,
    "Title": "Engineering Assistant",
    "Dept": "Engineering",
    "EMailAddress": "Ranee.Anderson@aqua-aerobic.com",
    "Manager": "NULL",
    "Photo": "NULL",
    "FloorMap": "NULL",
    "URL": "https://aquaaerobicsystem.github.io/aquadirectory/index.html?app=aquadirectory&width=715&height=21&floor=first",
    "Location": ""
  },
  {
    "EmployeeID": 384,
    "Last_Name": "Spurlock",
    "First_Name": "Karen",
    "Ext": 4473,
    "Title": "Executive Assistant",
    "Dept": "Engineering",
    "EMailAddress": "KSpurlock@aqua-aerobic.com",
    "Manager": "NULL",
    "Photo": "NULL",
    "FloorMap": "NULL",
    "URL": "https://aquaaerobicsystem.github.io/aquadirectory/index.html?app=aquadirectory&width=715&height=21&floor=first",
    "Location": ""
  },
  {
    "EmployeeID": 401,
    "Last_Name": "Outside",
    "First_Name": "Receptionist",
    "Ext": 4500,
    "Title": "-Enter Employee Title",
    "Dept": "-Enter Employee Department",
    "EMailAddress": "FirstInititalAndLastName@aqua-aerobic.com",
    "Manager": "NULL",
    "Photo": "NULL",
    "FloorMap": "NULL",
    "URL": "https://aquaaerobicsystem.github.io/aquadirectory/index.html?app=aquadirectory&width=715&height=21&floor=first",
    "Location": ""
  },
  {
    "EmployeeID": 606,
    "Last_Name": "Arbisi",
    "First_Name": "Sandra",
    "Ext": 0,
    "Title": "Receptionist/Doc.Control Asst.",
    "Dept": "Administration",
    "EMailAddress": "rarbisi@aqua-aerobic.com",
    "Manager": "NULL",
    "Photo": "NULL",
    "FloorMap": "NULL",
    "URL": "https://aquaaerobicsystem.github.io/aquadirectory/index.html?app=aquadirectory&width=715&height=21&floor=first",
    "Location": ""
  },
  {
    "EmployeeID": 610,
    "Last_Name": "Davila",
    "First_Name": "Angelica",
    "Ext": 4563,
    "Title": "Project Applications Engineer",
    "Dept": "Applications Engineering",
    "EMailAddress": "adavila@aqua-aerobic.com",
    "Manager": "NULL",
    "Photo": "NULL",
    "FloorMap": "NULL",
    "URL": "https://aquaaerobicsystem.github.io/aquadirectory/index.html?app=aquadirectory&width=715&height=21&floor=first",
    "Location": ""
  },
  {
    "EmployeeID": 612,
    "Last_Name": "Meyer",
    "First_Name": "Dave",
    "Ext": 4401,
    "Title": "Procurement Manager",
    "Dept": "Operations",
    "EMailAddress": "dmeyer@aqua-aerobic.com",
    "Manager": "NULL",
    "Photo": "NULL",
    "FloorMap": "NULL",
    "URL": "https://aquaaerobicsystem.github.io/aquadirectory/index.html?app=aquadirectory&width=715&height=21&floor=first",
    "Location": ""
  },
  {
    "EmployeeID": 615,
    "Last_Name": "Mazzei",
    "First_Name": "Tatiana",
    "Ext": 4409,
    "Title": "Project Applications Engineer",
    "Dept": "Applications Engineering",
    "EMailAddress": "tmazzei@aqua-aerobic.com",
    "Manager": "NULL",
    "Photo": "NULL",
    "FloorMap": "NULL",
    "URL": "https://aquaaerobicsystem.github.io/aquadirectory/index.html?app=aquadirectory&width=715&height=21&floor=first",
    "Location": ""
  },
  {
    "EmployeeID": 616,
    "Last_Name": "Brady, P.E.",
    "First_Name": "Dawn",
    "Ext": 4462,
    "Title": "Application Engineer",
    "Dept": "Applications Engineering",
    "EMailAddress": "dbrady@aqua-aerobic.com",
    "Manager": "NULL",
    "Photo": "NULL",
    "FloorMap": "NULL",
    "URL": "https://aquaaerobicsystem.github.io/aquadirectory/index.html?app=aquadirectory&width=715&height=21&floor=first",
    "Location": ""
  },
  {
    "EmployeeID": 617,
    "Last_Name": "Stiles",
    "First_Name": "Deb",
    "Ext": 4550,
    "Title": "Engineering Assistant",
    "Dept": "Engineering",
    "EMailAddress": "DStiles@aqua-aerobic.com",
    "Manager": "NULL",
    "Photo": "NULL",
    "FloorMap": "NULL",
    "URL": "https://aquaaerobicsystem.github.io/aquadirectory/index.html?app=aquadirectory&width=715&height=21&floor=first",
    "Location": ""
  },
  {
    "EmployeeID": 618,
    "Last_Name": "Barber",
    "First_Name": "Niki",
    "Ext": 4502,
    "Title": "Cost/Staff Accountant",
    "Dept": "Accounting",
    "EMailAddress": "NBarber@aqua-aerobic.com",
    "Manager": "NULL",
    "Photo": "NULL",
    "FloorMap": "NULL",
    "URL": "https://aquaaerobicsystem.github.io/aquadirectory/index.html?app=aquadirectory&width=715&height=21&floor=first",
    "Location": ""
  },
  {
    "EmployeeID": 620,
    "Last_Name": "Gentner",
    "First_Name": "Alicia",
    "Ext": 4575,
    "Title": "Shop",
    "Dept": "Shop",
    "EMailAddress": "AGentner@aqua-aerobic.com",
    "Manager": "NULL",
    "Photo": "NULL",
    "FloorMap": "NULL",
    "URL": "https://aquaaerobicsystem.github.io/aquadirectory/index.html?app=aquadirectory&width=715&height=21&floor=first",
    "Location": ""
  },
  {
    "EmployeeID": 623,
    "Last_Name": "Williams",
    "First_Name": "Steve",
    "Ext": 4529,
    "Title": "IT Manager",
    "Dept": "MIS",
    "EMailAddress": "SWilliams@aqua-aerobic.com",
    "Manager": "NULL",
    "Photo": "NULL",
    "FloorMap": "NULL",
    "URL": "https://aquaaerobicsystem.github.io/aquadirectory/index.html?app=aquadirectory&width=715&height=21&floor=first",
    "Location": ""
  },
  {
    "EmployeeID": 625,
    "Last_Name": "Ferguson",
    "First_Name": "Wendy",
    "Ext": 1310,
    "Title": "Field Service Representative",
    "Dept": "Field Service",
    "EMailAddress": "",
    "Manager": "NULL",
    "Photo": "NULL",
    "FloorMap": "NULL",
    "URL": "https://aquaaerobicsystem.github.io/aquadirectory/index.html?app=aquadirectory&width=715&height=21&floor=first",
    "Location": ""
  },
  {
    "EmployeeID": 627,
    "Last_Name": "Stanish",
    "First_Name": "Steve",
    "Ext": 4489,
    "Title": "Regional Manager",
    "Dept": "Domestic Sales",
    "EMailAddress": "sstanish@aqua-aerobic.com",
    "Manager": "NULL",
    "Photo": "NULL",
    "FloorMap": "NULL",
    "URL": "https://aquaaerobicsystem.github.io/aquadirectory/index.html?app=aquadirectory&width=715&height=21&floor=first",
    "Location": ""
  },
  {
    "EmployeeID": 628,
    "Last_Name": "Podraza",
    "First_Name": "Dee",
    "Ext": 4412,
    "Title": "Payroll / Accounting Specialist",
    "Dept": "Accounting",
    "EMailAddress": "DPodraza@aqua-aerobic.com",
    "Manager": "NULL",
    "Photo": "NULL",
    "FloorMap": "NULL",
    "URL": "https://aquaaerobicsystem.github.io/aquadirectory/index.html?app=aquadirectory&width=715&height=21&floor=first",
    "Location": ""
  },
  {
    "EmployeeID": 630,
    "Last_Name": "Summers",
    "First_Name": "John",
    "Ext": 4598,
    "Title": "Sr. Programmer/Analyst",
    "Dept": "MIS",
    "EMailAddress": "jsummers@aqua-aerobic.com",
    "Manager": "NULL",
    "Photo": "NULL",
    "FloorMap": "NULL",
    "URL": "https://aquaaerobicsystem.github.io/aquadirectory/index.html?app=aquadirectory&width=715&height=21&floor=first",
    "Location": ""
  },
  {
    "EmployeeID": 633,
    "Last_Name": "Boehm",
    "First_Name": "Denise",
    "Ext": 4461,
    "Title": "Aftermarket Sales Representative",
    "Dept": "Aftermarket Sales",
    "EMailAddress": "DBoehm@aqua-aerobic.com",
    "Manager": "NULL",
    "Photo": "NULL",
    "FloorMap": "NULL",
    "URL": "https://aquaaerobicsystem.github.io/aquadirectory/index.html?app=aquadirectory&width=715&height=21&floor=first",
    "Location": ""
  },
  {
    "EmployeeID": 635,
    "Last_Name": "Glauch",
    "First_Name": "Aaron",
    "Ext": 4507,
    "Title": "Senior Process Engineer",
    "Dept": "Applications Engineering",
    "EMailAddress": "AGlauch@aqua-aerobic.com",
    "Manager": "NULL",
    "Photo": "NULL",
    "FloorMap": "NULL",
    "URL": "https://aquaaerobicsystem.github.io/aquadirectory/index.html?app=aquadirectory&width=715&height=21&floor=first",
    "Location": ""
  },
  {
    "EmployeeID": 637,
    "Last_Name": "Gunderson",
    "First_Name": "Monica",
    "Ext": 4511,
    "Title": "Seminar Coordinator",
    "Dept": "Marketing",
    "EMailAddress": "MGunderson@aqua-aerobic.com",
    "Manager": "NULL",
    "Photo": "NULL",
    "FloorMap": "NULL",
    "URL": "https://aquaaerobicsystem.github.io/aquadirectory/index.html?app=aquadirectory&width=715&height=21&floor=first",
    "Location": ""
  },
  {
    "EmployeeID": 640,
    "Last_Name": "Lockhart",
    "First_Name": "Daniel",
    "Ext": 4520,
    "Title": "Customer Service Process Specialist",
    "Dept": "Aftermarket Sales",
    "EMailAddress": "dlockhart@aqua-aerobic.com",
    "Manager": "NULL",
    "Photo": "NULL",
    "FloorMap": "NULL",
    "URL": "https://aquaaerobicsystem.github.io/aquadirectory/index.html?app=aquadirectory&width=715&height=21&floor=first",
    "Location": ""
  },
  {
    "EmployeeID": 641,
    "Last_Name": "Gravagno",
    "First_Name": "Darryl",
    "Ext": 4438,
    "Title": "Senior Research and Development Engineer",
    "Dept": "R&D",
    "EMailAddress": "dgravagno@aqua-aerobic.com",
    "Manager": "NULL",
    "Photo": "NULL",
    "FloorMap": "NULL",
    "URL": "https://aquaaerobicsystem.github.io/aquadirectory/index.html?app=aquadirectory&width=715&height=21&floor=first",
    "Location": ""
  },
  {
    "EmployeeID": 642,
    "Last_Name": "Uchacz",
    "First_Name": "Denise",
    "Ext": 4514,
    "Title": "Aftermarket Sales Representative",
    "Dept": "Aftermarket Sales",
    "EMailAddress": "DUchacz@aqua-aerobic.com",
    "Manager": "NULL",
    "Photo": "NULL",
    "FloorMap": "NULL",
    "URL": "https://aquaaerobicsystem.github.io/aquadirectory/index.html?app=aquadirectory&width=715&height=21&floor=first",
    "Location": ""
  },
  {
    "EmployeeID": 643,
    "Last_Name": "Bell",
    "First_Name": "Cheryl",
    "Ext": 4444,
    "Title": "Production Assistant",
    "Dept": "Production",
    "EMailAddress": "cbell@aqua-aerobic.com",
    "Manager": "NULL",
    "Photo": "NULL",
    "FloorMap": "NULL",
    "URL": "https://aquaaerobicsystem.github.io/aquadirectory/index.html?app=aquadirectory&width=715&height=21&floor=first",
    "Location": ""
  },
  {
    "EmployeeID": 645,
    "Last_Name": "Sims",
    "First_Name": "Will",
    "Ext": 1300,
    "Title": "Field Service Representative",
    "Dept": "Field Service",
    "EMailAddress": "wsims@aqua-aerobic.com",
    "Manager": "NULL",
    "Photo": "NULL",
    "FloorMap": "NULL",
    "URL": "https://aquaaerobicsystem.github.io/aquadirectory/index.html?app=aquadirectory&width=715&height=21&floor=first",
    "Location": ""
  },
  {
    "EmployeeID": 647,
    "Last_Name": "Morrison",
    "First_Name": "Carla",
    "Ext": 4518,
    "Title": "Buyer",
    "Dept": "Purchasing",
    "EMailAddress": "CMorrison@aqua-aerobic.com",
    "Manager": "NULL",
    "Photo": "NULL",
    "FloorMap": "NULL",
    "URL": "https://aquaaerobicsystem.github.io/aquadirectory/index.html?app=aquadirectory&width=715&height=21&floor=first",
    "Location": ""
  },
  {
    "EmployeeID": 649,
    "Last_Name": "Quimby",
    "First_Name": "Brett",
    "Ext": 4572,
    "Title": "Senior Process Engineer-AquaNereda",
    "Dept": "Applications Engineering",
    "EMailAddress": "BQuimby@aqua-aerobic.com",
    "Manager": "NULL",
    "Photo": "NULL",
    "FloorMap": "NULL",
    "URL": "https://aquaaerobicsystem.github.io/aquadirectory/index.html?app=aquadirectory&width=715&height=21&floor=first",
    "Location": ""
  },
  {
    "EmployeeID": 651,
    "Last_Name": "Peterson",
    "First_Name": "Lynn",
    "Ext": 4544,
    "Title": "-Enter Employee Title",
    "Dept": "-Enter Employee Dept",
    "EMailAddress": "LPeterson@aqua-aerobic.com",
    "Manager": "NULL",
    "Photo": "NULL",
    "FloorMap": "NULL",
    "URL": "https://aquaaerobicsystem.github.io/aquadirectory/index.html?app=aquadirectory&width=715&height=21&floor=first",
    "Location": ""
  },
  {
    "EmployeeID": 652,
    "Last_Name": "DeLang",
    "First_Name": "Erich",
    "Ext": 4562,
    "Title": "Product Specialist",
    "Dept": "RP",
    "EMailAddress": "EDeLang@aqua-aerobic.com",
    "Manager": "NULL",
    "Photo": "NULL",
    "FloorMap": "NULL",
    "URL": "https://aquaaerobicsystem.github.io/aquadirectory/index.html?app=aquadirectory&width=715&height=21&floor=first",
    "Location": ""
  },
  {
    "EmployeeID": 656,
    "Last_Name": "Dyson",
    "First_Name": "John",
    "Ext": 4506,
    "Title": "Product Channel Manager",
    "Dept": "Product Management",
    "EMailAddress": "jdyson@aqua-aerobic.com",
    "Manager": "NULL",
    "Photo": "NULL",
    "FloorMap": "NULL",
    "URL": "https://aquaaerobicsystem.github.io/aquadirectory/index.html?app=aquadirectory&width=715&height=21&floor=first",
    "Location": ""
  },
  {
    "EmployeeID": 657,
    "Last_Name": "Shimada",
    "First_Name": "H",
    "Ext": 4405,
    "Title": "-Enter Employee Title",
    "Dept": "-Enter Employee Department",
    "EMailAddress": "hshimada@aqua-aerobic.com",
    "Manager": "NULL",
    "Photo": "NULL",
    "FloorMap": "NULL",
    "URL": "https://aquaaerobicsystem.github.io/aquadirectory/index.html?app=aquadirectory&width=715&height=21&floor=first",
    "Location": ""
  },
  {
    "EmployeeID": 661,
    "Last_Name": "Hoffman",
    "First_Name": "Blake",
    "Ext": 4491,
    "Title": "Project Manager",
    "Dept": "Project Management",
    "EMailAddress": "BHoffman@aqua-aerobic.com",
    "Manager": "NULL",
    "Photo": "NULL",
    "FloorMap": "NULL",
    "URL": "https://aquaaerobicsystem.github.io/aquadirectory/index.html?app=aquadirectory&width=715&height=21&floor=first",
    "Location": ""
  },
  {
    "EmployeeID": 662,
    "Last_Name": "Appino",
    "First_Name": "Pam",
    "Ext": 4456,
    "Title": "Director of HR",
    "Dept": "Human Resources",
    "EMailAddress": "PAppino@aqua-aerobic.com",
    "Manager": "NULL",
    "Photo": "NULL",
    "FloorMap": "NULL",
    "URL": "https://aquaaerobicsystem.github.io/aquadirectory/index.html?app=aquadirectory&width=715&height=21&floor=first",
    "Location": ""
  },
  {
    "EmployeeID": 664,
    "Last_Name": "Morton",
    "First_Name": "Ben",
    "Ext": 1303,
    "Title": "Field Service Specialist",
    "Dept": "Field Service",
    "EMailAddress": "BMorton@aqua-aerobic.com",
    "Manager": "NULL",
    "Photo": "NULL",
    "FloorMap": "NULL",
    "URL": "https://aquaaerobicsystem.github.io/aquadirectory/index.html?app=aquadirectory&width=715&height=21&floor=first",
    "Location": ""
  },
  {
    "EmployeeID": 665,
    "Last_Name": "Altimimi",
    "First_Name": "Sara",
    "Ext": 4545,
    "Title": "Application Engineer",
    "Dept": "Applications Engineering",
    "EMailAddress": "SAltimimi@aqua-aerobic.com",
    "Manager": "NULL",
    "Photo": "NULL",
    "FloorMap": "NULL",
    "URL": "https://aquaaerobicsystem.github.io/aquadirectory/index.html?app=aquadirectory&width=715&height=21&floor=first",
    "Location": ""
  },
  {
    "EmployeeID": 666,
    "Last_Name": "Ustich",
    "First_Name": "Gennie",
    "Ext": 4455,
    "Title": "Human Resource Specialist",
    "Dept": "Human Resources",
    "EMailAddress": "GUstich@aqua-aerobic.com",
    "Manager": "NULL",
    "Photo": "NULL",
    "FloorMap": "NULL",
    "URL": "https://aquaaerobicsystem.github.io/aquadirectory/index.html?app=aquadirectory&width=715&height=21&floor=first",
    "Location": ""
  },
  {
    "EmployeeID": 667,
    "Last_Name": "Christian",
    "First_Name": "Brad",
    "Ext": 4560,
    "Title": "Electrical Engineer",
    "Dept": "Electrical Engineering",
    "EMailAddress": "BChristian@aqua-aerobic.com",
    "Manager": "NULL",
    "Photo": "NULL",
    "FloorMap": "NULL",
    "URL": "https://aquaaerobicsystem.github.io/aquadirectory/index.html?app=aquadirectory&width=715&height=21&floor=first",
    "Location": ""
  },
  {
    "EmployeeID": 668,
    "Last_Name": "Ruggles",
    "First_Name": "Tasha",
    "Ext": 4508,
    "Title": "Credit Specialist",
    "Dept": "Accounting",
    "EMailAddress": "truggles@aqua-aerobic.com",
    "Manager": "NULL",
    "Photo": "NULL",
    "FloorMap": "NULL",
    "URL": "https://aquaaerobicsystem.github.io/aquadirectory/index.html?app=aquadirectory&width=715&height=21&floor=first",
    "Location": ""
  },
  {
    "EmployeeID": 669,
    "Last_Name": "Sakashita",
    "First_Name": "Junji",
    "Ext": 4512,
    "Title": "Electrical Engineer",
    "Dept": "Electrical Engineering",
    "EMailAddress": "JSakashita@aqua-aerobic.com",
    "Manager": "NULL",
    "Photo": "NULL",
    "FloorMap": "NULL",
    "URL": "https://aquaaerobicsystem.github.io/aquadirectory/index.html?app=aquadirectory&width=715&height=21&floor=first",
    "Location": ""
  },
  {
    "EmployeeID": 670,
    "Last_Name": "Disbrow",
    "First_Name": "Kathleen",
    "Ext": 4548,
    "Title": "Buyer",
    "Dept": "Purchasing",
    "EMailAddress": "KDisbrow@aqua-aerobic.com",
    "Manager": "NULL",
    "Photo": "NULL",
    "FloorMap": "NULL",
    "URL": "https://aquaaerobicsystem.github.io/aquadirectory/index.html?app=aquadirectory&width=715&height=21&floor=first",
    "Location": ""
  },
  {
    "EmployeeID": 671,
    "Last_Name": "Bates",
    "First_Name": "Brian",
    "Ext": 4451,
    "Title": "Product Manager",
    "Dept": "Product Management",
    "EMailAddress": "BBates@aqua-aerobic.com",
    "Manager": "NULL",
    "Photo": "NULL",
    "FloorMap": "NULL",
    "URL": "https://aquaaerobicsystem.github.io/aquadirectory/index.html?app=aquadirectory&width=715&height=21&floor=first",
    "Location": ""
  },
  {
    "EmployeeID": 674,
    "Last_Name": "Nora",
    "First_Name": "Mike",
    "Ext": 4465,
    "Title": "Project Applications Engineer",
    "Dept": "Applications Engineering",
    "EMailAddress": "MNora@aqua-aerobic.com",
    "Manager": "NULL",
    "Photo": "NULL",
    "FloorMap": "NULL",
    "URL": "https://aquaaerobicsystem.github.io/aquadirectory/index.html?app=aquadirectory&width=715&height=21&floor=first",
    "Location": ""
  },
  {
    "EmployeeID": 675,
    "Last_Name": "StockRoom",
    "First_Name": "Phone",
    "Ext": 6261,
    "Title": "StockRoom",
    "Dept": "Shop",
    "EMailAddress": "DAnderson@aqua-aerobic.com",
    "Manager": "NULL",
    "Photo": "NULL",
    "FloorMap": "NULL",
    "URL": "https://aquaaerobicsystem.github.io/aquadirectory/index.html?app=aquadirectory&width=715&height=21&floor=first",
    "Location": ""
  },
  {
    "EmployeeID": 678,
    "Last_Name": "Loh",
    "First_Name": "SooMin",
    "Ext": 1323,
    "Title": "Engineer",
    "Dept": "Ohio",
    "EMailAddress": "SLoh@aqua-aerobic.com",
    "Manager": "NULL",
    "Photo": "NULL",
    "FloorMap": "NULL",
    "URL": "https://aquaaerobicsystem.github.io/aquadirectory/index.html?app=aquadirectory&width=715&height=21&floor=first",
    "Location": ""
  },
  {
    "EmployeeID": 679,
    "Last_Name": "Anderson",
    "First_Name": "Mondi",
    "Ext": 1324,
    "Title": "Engineer",
    "Dept": "Ohio",
    "EMailAddress": "MAnderson@aqua-aerobic.com",
    "Manager": "NULL",
    "Photo": "NULL",
    "FloorMap": "NULL",
    "URL": "https://aquaaerobicsystem.github.io/aquadirectory/index.html?app=aquadirectory&width=715&height=21&floor=first",
    "Location": ""
  },
  {
    "EmployeeID": 680,
    "Last_Name": "Smith",
    "First_Name": "Tony",
    "Ext": 1317,
    "Title": "Field Service",
    "Dept": "Ohio",
    "EMailAddress": "TSmith@aqua-aerobic.com",
    "Manager": "NULL",
    "Photo": "NULL",
    "FloorMap": "NULL",
    "URL": "https://aquaaerobicsystem.github.io/aquadirectory/index.html?app=aquadirectory&width=715&height=21&floor=first",
    "Location": ""
  },
  {
    "EmployeeID": 681,
    "Last_Name": "Watson",
    "First_Name": "Ohta",
    "Ext": 1318,
    "Title": "Field Service",
    "Dept": "Ohio",
    "EMailAddress": "OWatson@aqua-aerobic.com",
    "Manager": "NULL",
    "Photo": "NULL",
    "FloorMap": "NULL",
    "URL": "https://aquaaerobicsystem.github.io/aquadirectory/index.html?app=aquadirectory&width=715&height=21&floor=first",
    "Location": ""
  },
  {
    "EmployeeID": 682,
    "Last_Name": "Campanaro",
    "First_Name": "Joe",
    "Ext": 1325,
    "Title": "Pilot Engineer",
    "Dept": "Engineering",
    "EMailAddress": "JCampanaro@aqua-aerobic.com",
    "Manager": "NULL",
    "Photo": "NULL",
    "FloorMap": "NULL",
    "URL": "https://aquaaerobicsystem.github.io/aquadirectory/index.html?app=aquadirectory&width=715&height=21&floor=first",
    "Location": ""
  },
  {
    "EmployeeID": 684,
    "Last_Name": "Nowicki",
    "First_Name": "Jakob",
    "Ext": 4487,
    "Title": "Project Applications Engineer",
    "Dept": "Applications Engineering",
    "EMailAddress": "JNowicki@aqua-aerobic.com",
    "Manager": "NULL",
    "Photo": "NULL",
    "FloorMap": "NULL",
    "URL": "https://aquaaerobicsystem.github.io/aquadirectory/index.html?app=aquadirectory&width=715&height=21&floor=first",
    "Location": ""
  },
  {
    "EmployeeID": 685,
    "Last_Name": "Torrisi",
    "First_Name": "Leann",
    "Ext": 4522,
    "Title": "Administrative Assistant - AMS",
    "Dept": "Aftermarket Sales",
    "EMailAddress": "LTorrisi@aqua-aerobic.com",
    "Manager": "NULL",
    "Photo": "NULL",
    "FloorMap": "NULL",
    "URL": "https://aquaaerobicsystem.github.io/aquadirectory/index.html?app=aquadirectory&width=715&height=21&floor=first",
    "Location": ""
  },
  {
    "EmployeeID": 686,
    "Last_Name": "Kurshinsky",
    "First_Name": "Chris",
    "Ext": 4403,
    "Title": "Pilot System Technician",
    "Dept": "Engineering - Standards",
    "EMailAddress": "CKurshinsky@aqua-aerobic.com",
    "Manager": "NULL",
    "Photo": "NULL",
    "FloorMap": "NULL",
    "URL": "https://aquaaerobicsystem.github.io/aquadirectory/index.html?app=aquadirectory&width=715&height=21&floor=first",
    "Location": ""
  },
  {
    "EmployeeID": 687,
    "Last_Name": "Ogle",
    "First_Name": "Jeff",
    "Ext": 4424,
    "Title": "Aftermarket External Sales Specialist",
    "Dept": "Aftermarket Sales",
    "EMailAddress": "JOgle@aqua-aerobic.com",
    "Manager": "NULL",
    "Photo": "NULL",
    "FloorMap": "NULL",
    "URL": "https://aquaaerobicsystem.github.io/aquadirectory/index.html?app=aquadirectory&width=715&height=21&floor=first",
    "Location": ""
  },
  {
    "EmployeeID": 688,
    "Last_Name": "Pasterczyk",
    "First_Name": "JP",
    "Ext": 4464,
    "Title": "Industrial Sales Manager",
    "Dept": "Sales",
    "EMailAddress": "JPasterczyk@aqua-aerobic.com",
    "Manager": "NULL",
    "Photo": "NULL",
    "FloorMap": "NULL",
    "URL": "https://aquaaerobicsystem.github.io/aquadirectory/index.html?app=aquadirectory&width=715&height=21&floor=first",
    "Location": ""
  },
  {
    "EmployeeID": 689,
    "Last_Name": "Kelly",
    "First_Name": "Scott",
    "Ext": 4467,
    "Title": "Regional Sales Manager",
    "Dept": "Domestic Sales",
    "EMailAddress": "SKelly@aqua-aerobic.com",
    "Manager": "NULL",
    "Photo": "NULL",
    "FloorMap": "NULL",
    "URL": "https://aquaaerobicsystem.github.io/aquadirectory/index.html?app=aquadirectory&width=715&height=21&floor=first",
    "Location": ""
  },
  {
    "EmployeeID": 690,
    "Last_Name": "Edelen",
    "First_Name": "John",
    "Ext": 1306,
    "Title": "Field Service Specialist",
    "Dept": "Field Service",
    "EMailAddress": "JEdelen@aqua-aerobic.com",
    "Manager": "NULL",
    "Photo": "NULL",
    "FloorMap": "NULL",
    "URL": "https://aquaaerobicsystem.github.io/aquadirectory/index.html?app=aquadirectory&width=715&height=21&floor=first",
    "Location": ""
  },
  {
    "EmployeeID": 691,
    "Last_Name": "Smith",
    "First_Name": "Geoffrey",
    "Ext": 1326,
    "Title": "Field Service Specialist",
    "Dept": "Field Service",
    "EMailAddress": "GSmith@aqua-aerobic.com",
    "Manager": "NULL",
    "Photo": "NULL",
    "FloorMap": "NULL",
    "URL": "https://aquaaerobicsystem.github.io/aquadirectory/index.html?app=aquadirectory&width=715&height=21&floor=first",
    "Location": ""
  },
  {
    "EmployeeID": 692,
    "Last_Name": "Spragg",
    "First_Name": "Mike",
    "Ext": 4597,
    "Title": "Technical Support Specialist",
    "Dept": "Customer Service",
    "EMailAddress": "MSpragg@aqua-aerobic.com",
    "Manager": "NULL",
    "Photo": "NULL",
    "FloorMap": "NULL",
    "URL": "https://aquaaerobicsystem.github.io/aquadirectory/index.html?app=aquadirectory&width=715&height=21&floor=first",
    "Location": ""
  },
  {
    "EmployeeID": 693,
    "Last_Name": "Khoga",
    "First_Name": "Shareef",
    "Ext": 4435,
    "Title": "Project Manager",
    "Dept": "Project Management",
    "EMailAddress": "SKhoga@aqua-aerobic.com",
    "Manager": "NULL",
    "Photo": "NULL",
    "FloorMap": "NULL",
    "URL": "https://aquaaerobicsystem.github.io/aquadirectory/index.html?app=aquadirectory&width=715&height=21&floor=first",
    "Location": ""
  },
  {
    "EmployeeID": 694,
    "Last_Name": "Miles",
    "First_Name": "Tom",
    "Ext": 4463,
    "Title": "Regional Sales Manager",
    "Dept": "Domestic Sales",
    "EMailAddress": "TMiles@aqua-aerobic.com",
    "Manager": "NULL",
    "Photo": "NULL",
    "FloorMap": "NULL",
    "URL": "https://aquaaerobicsystem.github.io/aquadirectory/index.html?app=aquadirectory&width=715&height=21&floor=first",
    "Location": ""
  },
  {
    "EmployeeID": 695,
    "Last_Name": "Patch",
    "First_Name": "Jay",
    "Ext": 4441,
    "Title": "Logistics Coordinator",
    "Dept": "Shipping/Receiving",
    "EMailAddress": "JPatch@aqua-aerobic.com",
    "Manager": "NULL",
    "Photo": "NULL",
    "FloorMap": "NULL",
    "URL": "https://aquaaerobicsystem.github.io/aquadirectory/index.html?app=aquadirectory&width=715&height=21&floor=first",
    "Location": ""
  },
  {
    "EmployeeID": 696,
    "Last_Name": "Butterfield",
    "First_Name": "Shawn",
    "Ext": 4490,
    "Title": "Technical Support Specialist",
    "Dept": "Customer Service",
    "EMailAddress": "SButterfield@aqua-aerobic.com",
    "Manager": "NULL",
    "Photo": "NULL",
    "FloorMap": "NULL",
    "URL": "https://aquaaerobicsystem.github.io/aquadirectory/index.html?app=aquadirectory&width=715&height=21&floor=first",
    "Location": ""
  },
  {
    "EmployeeID": 698,
    "Last_Name": "Price",
    "First_Name": "Evan",
    "Ext": 4594,
    "Title": "R&D Engineer",
    "Dept": "R&D",
    "EMailAddress": "EPrice@aqua-aerobic.com",
    "Manager": "NULL",
    "Photo": "NULL",
    "FloorMap": "NULL",
    "URL": "https://aquaaerobicsystem.github.io/aquadirectory/index.html?app=aquadirectory&width=715&height=21&floor=first",
    "Location": ""
  },
  {
    "EmployeeID": 700,
    "Last_Name": "Rice",
    "First_Name": "Alan",
    "Ext": 4553,
    "Title": "Product Manager - Aeration and Mixing",
    "Dept": "Rotating Products",
    "EMailAddress": "ARice@aqua-aerobic.com",
    "Manager": "NULL",
    "Photo": "NULL",
    "FloorMap": "NULL",
    "URL": "https://aquaaerobicsystem.github.io/aquadirectory/index.html?app=aquadirectory&width=715&height=21&floor=first",
    "Location": ""
  },
  {
    "EmployeeID": 701,
    "Last_Name": "Kullberg",
    "First_Name": "Emily",
    "Ext": 4494,
    "Title": "Sales Correspondent",
    "Dept": "Applications Engineering",
    "EMailAddress": "EKullberg@aqua-aerobic.com",
    "Manager": "NULL",
    "Photo": "NULL",
    "FloorMap": "NULL",
    "URL": "https://aquaaerobicsystem.github.io/aquadirectory/index.html?app=aquadirectory&width=715&height=21&floor=first",
    "Location": ""
  },
  {
    "EmployeeID": 702,
    "Last_Name": "Dorn",
    "First_Name": "Paula",
    "Ext": 4528,
    "Title": "Process Engineer-Filtration",
    "Dept": "Applications Engineering",
    "EMailAddress": "PDorn@aqua-aerobic.com",
    "Manager": "NULL",
    "Photo": "NULL",
    "FloorMap": "NULL",
    "URL": "https://aquaaerobicsystem.github.io/aquadirectory/index.html?app=aquadirectory&width=715&height=21&floor=first",
    "Location": ""
  },
  {
    "EmployeeID": 703,
    "Last_Name": "Villarreal",
    "First_Name": "Michaela",
    "Ext": 4472,
    "Title": "Rotating Products Sales Assistant",
    "Dept": "Rotating Products",
    "EMailAddress": "MVillarreal@aqua-aerobic.com",
    "Manager": "NULL",
    "Photo": "NULL",
    "FloorMap": "NULL",
    "URL": "https://aquaaerobicsystem.github.io/aquadirectory/index.html?app=aquadirectory&width=715&height=21&floor=first",
    "Location": ""
  },
  {
    "EmployeeID": 704,
    "Last_Name": "Rennell",
    "First_Name": "Josh",
    "Ext": 4488,
    "Title": "Application Engineer",
    "Dept": "Applications Engineering",
    "EMailAddress": "JRennell@aqua-aerobic.com",
    "Manager": "NULL",
    "Photo": "NULL",
    "FloorMap": "NULL",
    "URL": "https://aquaaerobicsystem.github.io/aquadirectory/index.html?app=aquadirectory&width=715&height=21&floor=first",
    "Location": ""
  },
  {
    "EmployeeID": 707,
    "Last_Name": "Bennett",
    "First_Name": "Krista",
    "Ext": 4539,
    "Title": "Contract Administrator Aeration/Mixing",
    "Dept": "Product Management - Aeration/Mixing",
    "EMailAddress": "KBennett@aqua-aerobic.com",
    "Manager": "NULL",
    "Photo": "NULL",
    "FloorMap": "NULL",
    "URL": "https://aquaaerobicsystem.github.io/aquadirectory/index.html?app=aquadirectory&width=715&height=21&floor=first",
    "Location": ""
  },
  {
    "EmployeeID": 708,
    "Last_Name": "Burk",
    "First_Name": "Brady",
    "Ext": 4443,
    "Title": "Buyer",
    "Dept": "Purchasing",
    "EMailAddress": "BBurk@aqua-aerobic.com",
    "Manager": "NULL",
    "Photo": "NULL",
    "FloorMap": "NULL",
    "URL": "https://aquaaerobicsystem.github.io/aquadirectory/index.html?app=aquadirectory&width=715&height=21&floor=first",
    "Location": ""
  },
  {
    "EmployeeID": 709,
    "Last_Name": "Frieze",
    "First_Name": "Josh",
    "Ext": 1312,
    "Title": "Field Service Specialist",
    "Dept": "Field Service",
    "EMailAddress": "JFrieze@aqua-aerobic.com",
    "Manager": "NULL",
    "Photo": "NULL",
    "FloorMap": "NULL",
    "URL": "https://aquaaerobicsystem.github.io/aquadirectory/index.html?app=aquadirectory&width=715&height=21&floor=first",
    "Location": ""
  },
  {
    "EmployeeID": 710,
    "Last_Name": "Tucker",
    "First_Name": "Jerry",
    "Ext": 1328,
    "Title": "Field Service Specialist",
    "Dept": "Customer Service",
    "EMailAddress": "JTucker@aqua-aerobic.com",
    "Manager": "NULL",
    "Photo": "NULL",
    "FloorMap": "NULL",
    "URL": "https://aquaaerobicsystem.github.io/aquadirectory/index.html?app=aquadirectory&width=715&height=21&floor=first",
    "Location": ""
  },
  {
    "EmployeeID": 711,
    "Last_Name": "Hopkins",
    "First_Name": "Mark",
    "Ext": 4437,
    "Title": "Operations Supervisor",
    "Dept": "Operations",
    "EMailAddress": "MHopkins@aqua-aerobic.com",
    "Manager": "NULL",
    "Photo": "NULL",
    "FloorMap": "NULL",
    "URL": "https://aquaaerobicsystem.github.io/aquadirectory/index.html?app=aquadirectory&width=715&height=21&floor=first",
    "Location": ""
  },
  {
    "EmployeeID": 712,
    "Last_Name": "Stanek",
    "First_Name": "Paul",
    "Ext": 4593,
    "Title": "Programmer",
    "Dept": "IT",
    "EMailAddress": "PStanek@aqua-aerobic.com",
    "Manager": "NULL",
    "Photo": "NULL",
    "FloorMap": "NULL",
    "URL": "https://aquaaerobicsystem.github.io/aquadirectory/index.html?app=aquadirectory&width=715&height=21&floor=first",
    "Location": ""
  },
  {
    "EmployeeID": 713,
    "Last_Name": "Aylward",
    "First_Name": "Malcolm",
    "Ext": 4570,
    "Title": "Buyer",
    "Dept": "Purchasing",
    "EMailAddress": "MAylward@aqua-aerobic.com",
    "Manager": "NULL",
    "Photo": "NULL",
    "FloorMap": "NULL",
    "URL": "https://aquaaerobicsystem.github.io/aquadirectory/index.html?app=aquadirectory&width=715&height=21&floor=first",
    "Location": ""
  },
  {
    "EmployeeID": 714,
    "Last_Name": "Chycota",
    "First_Name": "Kristy",
    "Ext": 4523,
    "Title": "Application Engineer",
    "Dept": "Applications Engineering",
    "EMailAddress": "KChycota@aqua-aerobic.com",
    "Manager": "NULL",
    "Photo": "NULL",
    "FloorMap": "NULL",
    "URL": "https://aquaaerobicsystem.github.io/aquadirectory/index.html?app=aquadirectory&width=715&height=21&floor=first",
    "Location": ""
  },
  {
    "EmployeeID": 715,
    "Last_Name": "Davis",
    "First_Name": "Thea",
    "Ext": 4568,
    "Title": "Application Engineer",
    "Dept": "Applications Engineering",
    "EMailAddress": "TDavis@aqua-aerobic.com",
    "Manager": "NULL",
    "Photo": "NULL",
    "FloorMap": "NULL",
    "URL": "https://aquaaerobicsystem.github.io/aquadirectory/index.html?app=aquadirectory&width=715&height=21&floor=first",
    "Location": ""
  },
  {
    "EmployeeID": 716,
    "Last_Name": "Fortsas",
    "First_Name": "Nicholas",
    "Ext": 62203,
    "Title": "Applications Engineering Intern",
    "Dept": "Applications Engineering",
    "EMailAddress": "NFortsas@aqua-aerobic.com",
    "Manager": "NULL",
    "Photo": "NULL",
    "FloorMap": "NULL",
    "URL": "https://aquaaerobicsystem.github.io/aquadirectory/index.html?app=aquadirectory&width=715&height=21&floor=first",
    "Location": ""
  },
  {
    "EmployeeID": 717,
    "Last_Name": "Ahmad",
    "First_Name": "Humza",
    "Ext": 6204,
    "Title": "Applications Engineering Intern",
    "Dept": "Applications Engineering",
    "EMailAddress": "HAhmad@aqua-aerobic.com",
    "Manager": "NULL",
    "Photo": "NULL",
    "FloorMap": "NULL",
    "URL": "https://aquaaerobicsystem.github.io/aquadirectory/index.html?app=aquadirectory&width=715&height=21&floor=first",
    "Location": ""
  },
  {
    "EmployeeID": 718,
    "Last_Name": "Kelly",
    "First_Name": "Aislen",
    "Ext": 6202,
    "Title": "Applications Engineering Intern",
    "Dept": "Applications Engineering",
    "EMailAddress": "AKelly@aqua-aerobic.com",
    "Manager": "NULL",
    "Photo": "NULL",
    "FloorMap": "NULL",
    "URL": "https://aquaaerobicsystem.github.io/aquadirectory/index.html?app=aquadirectory&width=715&height=21&floor=first",
    "Location": ""
  },
  {
    "EmployeeID": 719,
    "Last_Name": "Yalung",
    "First_Name": "Stephen",
    "Ext": 4557,
    "Title": "Mechanical Designer",
    "Dept": "Engineering",
    "EMailAddress": "SYalung@aqua-aerobic.com",
    "Manager": "NULL",
    "Photo": "NULL",
    "FloorMap": "NULL",
    "URL": "https://aquaaerobicsystem.github.io/aquadirectory/index.html?app=aquadirectory&width=715&height=21&floor=first",
    "Location": ""
  },
  {
    "EmployeeID": 720,
    "Last_Name": "Rivers",
    "First_Name": "Allan",
    "Ext": 4480,
    "Title": "Electrical Designer",
    "Dept": "Electrical Engineering",
    "EMailAddress": "ARivers@aqua-aerobic.com",
    "Manager": "NULL",
    "Photo": "NULL",
    "FloorMap": "NULL",
    "URL": "https://aquaaerobicsystem.github.io/aquadirectory/index.html?app=aquadirectory&width=715&height=21&floor=first",
    "Location": ""
  },
  {
    "EmployeeID": 721,
    "Last_Name": "Johnson",
    "First_Name": "Rebecca",
    "Ext": 4426,
    "Title": "Marketing Assistant",
    "Dept": "Marketing",
    "EMailAddress": "rebecca.johnson@aqua-aerobic.com",
    "Manager": "NULL",
    "Photo": "NULL",
    "FloorMap": "NULL",
    "URL": "https://aquaaerobicsystem.github.io/aquadirectory/index.html?app=aquadirectory&width=715&height=21&floor=first",
    "Location": ""
  },
  {
    "EmployeeID": 722,
    "Last_Name": "Bockhop",
    "First_Name": "Devon",
    "Ext": 4578,
    "Title": "Mechanical Designer",
    "Dept": "Mechanical Engineering",
    "EMailAddress": "DBockhop@aqua-aerobic.com",
    "Manager": "NULL",
    "Photo": "NULL",
    "FloorMap": "NULL",
    "URL": "https://aquaaerobicsystem.github.io/aquadirectory/index.html?app=aquadirectory&width=715&height=21&floor=first",
    "Location": ""
  },
  {
    "EmployeeID": 723,
    "Last_Name": "Torgersen",
    "First_Name": "Julie",
    "Ext": 4585,
    "Title": "Buyer",
    "Dept": "Purchasing",
    "EMailAddress": "JTorgersen@aqua-aerobic.com",
    "Manager": "NULL",
    "Photo": "NULL",
    "FloorMap": "NULL",
    "URL": "https://aquaaerobicsystem.github.io/aquadirectory/index.html?app=aquadirectory&width=715&height=21&floor=first",
    "Location": ""
  },
  {
    "EmployeeID": 724,
    "Last_Name": "Dellamater",
    "First_Name": "Noah",
    "Ext": 4537,
    "Title": "Mechanical Engineer",
    "Dept": "Engineering Standards",
    "EMailAddress": "NDellamater@aqua-aerobic.com",
    "Manager": "NULL",
    "Photo": "NULL",
    "FloorMap": "NULL",
    "URL": "https://aquaaerobicsystem.github.io/aquadirectory/index.html?app=aquadirectory&width=715&height=21&floor=first",
    "Location": ""
  },
  {
    "EmployeeID": 725,
    "Last_Name": "Sanchez",
    "First_Name": "Ed",
    "Ext": 1309,
    "Title": "Field Service Specialist",
    "Dept": "Customer Service",
    "EMailAddress": "ESanchez@aqua-aerobic.com",
    "Manager": "NULL",
    "Photo": "NULL",
    "FloorMap": "NULL",
    "URL": "https://aquaaerobicsystem.github.io/aquadirectory/index.html?app=aquadirectory&width=715&height=21&floor=first",
    "Location": ""
  }
]